sparksql_magic/__init__.py
sparksql_magic/sparksql.py
sparksql_magic-0.0.3.dist-info/LICENSE
sparksql_magic-0.0.3.dist-info/METADATA
sparksql_magic-0.0.3.dist-info/WHEEL
sparksql_magic-0.0.3.dist-info/top_level.txt
sparksql_magic-0.0.3.dist-info/RECORD
