Metadata-Version: 2.1
Name: sparksql-magic
Version: 0.0.3
Summary: Spark SQL magic command for Jupyter notebooks
Home-page: https://github.com/cryeo/sparksql-magic
Author: Chaerim Yeo
Author-email: yeochaerim@gmail.com
License: MIT License
Platform: UNKNOWN
Classifier: Development Status :: 2 - Pre-Alpha
Classifier: License :: OSI Approved :: MIT License
Classifier: Programming Language :: Python
Classifier: Programming Language :: Python :: 3
Classifier: Programming Language :: Python :: 3.6
Classifier: Topic :: Software Development :: Libraries :: Python Modules
Requires-Python: >=3.6
Requires-Dist: pyspark (>=2.3.0)
Requires-Dist: ipython (>=7.4.0)
